Workbook

Sheet Terraplenagem
A1: PLANILHA PADRÃO DE PROPOSTA - FORNECIMENTO DE SERVIÇO DE TERRAPLANAGEM
A2: Cliente: | B2: RONMA
A3: CNPJ: | B3: 05.635.205/0001-67
A4: Obra: | B4: A. F. EMPREENDIMENTOS IMOBILIARIOS LTDA EPP
A5: Local: | B5: CARAPINA, SERRA - ES
A6: FORNECIMENTO DE MÃO DE OBRA E EQUIPAMENTOS PARA SERVIÇO DE TERRAPLANAGEM
A7: Item | B7: Descrição | C7: Unid. | D7: QUANTIDADE | E7: Preço Unitário (R$) | F7: Valor Total
A8: 1 | B8: PRELIMINARES
A9: 1.1 | B9: Mobilização e desmobilização de equipe e equipamentos. | C9: VB | D9: 2 | E9: 12000 | F9: =D9*E9 -> 24000
A10: 2 | B10: LIMPEZA
A11: 2.1 | B11: Limpeza da camada vegetal, incluindo fornecimento de máquinas em perfeito estado de conservação, juntamente com seus respectivos operadores. (Camada de até 20 cm). | C11: M2 | D11: 13321.1 | E11: 1.32 | F11: =D11*E11 -> 17583.852
A12: 2.2 | B12: Carga / Descarga e Transporte da camada vegetal para bota fora licenciado (com documentação) incluindo fornecimento de caminhões e máquinas em perfeito estado de conservação, juntamente com seus respectivos motoristas e operadores. DMT ATE 12KM | C12: M3 | D12: =D11*0.3 -> 3996.33 | E12: 74.215 | F12: =D12*E12 -> 296587.63
A13: 3 | B13: ESCAVAÇÃO, CARGA / DESCARGA E TRANSPORTE
A14: 3.1 | B14: Escavação mecânica, Carga e Transporte de material de 1ª categoria e máquinas em perfeito estado de conservação, juntamente com seus respectivos operadores e motoristas. DMT ATE 1 KM. | C14: M3 | D14: 12981.27 | E14: 6.68 | F14: =D14*E14 -> 86714.884
A15: 4 | B15: ATERRO E COMPACTAÇÃO
A16: 4.1 | B16: Aterro, Espalhamento, Tratamento e Compactação do solo de material de 1ª categoria a 100% procto normal conforme normas vigentes, incluindo fornecimento de máquinas em perfeito estado de conservação, juntamente com seus respectivos operadores. | C16: M3 | D16: 12981.27 | E16: 10.7745 | F16: =D16*E16 -> 139866.69
A17: 4.2 | B17: Nivelamento e Regularização final da área OBS.: Material a ser definido | C17: M3 | D17: 0 | E17: 2.85 | F17: =D17*E17 -> 0
A18: PRAZO PARA EXECUÇÃO: xx DIAS TRABALHADOS | E18: VALOR TOTAL DO SERVIÇO: | F18: =SUM(F9:F17) -> 564753.06
A20: INFORMAÇÕES DE FATURAMENTO
A21: (OS PERCENTUAIS INFORMADOS DEVEM SEMPRE RESPEITAR AS LEGISLAÇÕES NACIONAIS, ESTADUAIS E MUNICIPAIS PERTINENTES)
A22: A | B22: FATURAMENTO DE PRESTAÇÃO DE SERVIÇOS (MÃO DE OBRA) | C22: 0.15 | D22: =F18*C22 -> 84712.959
A23: B | B23: FATURAMENTO DE EQUIPAMENTOS | C23: 0.85 | D23: =F18*C23 -> 480040.1
B24: PRAZOS (considerando a partir do início dos serviços):
A25: A.1 | B25: Mobilização de equipe e equipamentos. | C25: IMEDIATO MEDIANTE ACEITE DA PROPOSTA
A26: A.2 | B26: Execução dos serviços, considerando áreas 100% liberadas. | C26: XX DIAS APÓS ACEITE DA PROPOSTA (SEM INTERVENÇÕES TIPO CHUVA)
A28: CHECK LIST TÉCNICO | F28: CAMPO PARA CONFIRMAÇÃO CONTRATADA
A29: 1 | B29: Fornecimento de equipe que atenda o cronograma a ser apresentado no início da obra de modo a não atrasar o andamento dos serviços.
A30: 2 | B30: Mobilização e Desmobilização de todos equipamentos envolvidos na operação necessários para execução do serviço, incluindo seus respectivos motoristas e operadores (01 Escavadeira Hidráulica, 01 Motoniveladora, 01 Caminhão Pipa, 02 Rolo Compactador Pé de carneiro, 01 Trator Agrícola com Grade ou qualquer outro que seja necessário para execução do serviço, 05 Caminhões Caçamba Truck, 01 Caminhão Prancha, 01 Automóvel Apoio).
A31: 3 | B31: Fornecimento de Equipe de Topografia para suas respectivas marcações de greide de Terraplenagem e Paviemtação e quaisquer outras atividades que forem de responsabilidade da mesma, laboratório para acompanhamento e verificação do grau de compactação das camadas , entre outros, serão fornecidos PELA CONTRATANTE. Os projetos executivos e detalhes/orientações, serão fornecidos pela CONTRATANTE.
A32: 4 | B32: O critério de medições : • Mediante Levantamento Topográfico Mensal
A33: 5 | B33: O critério de Faturamento : • Emissão de Nota Fiscal e Boleto vencimento 10 Dias após emissão
A34: 6 | B34: O critério de execução : • Caso seja preciso quaisquer outros tipos de atividades para execução dos serviços seja interno ou externo, serão cobrados hora equipamentos em medições. • Quantitativos acima descritos podendo variar mediante levantamento topografico, caso haja alterações serão acrescidos ou descrescidas em medições.

Sheet Terraplenagem (2)
A1: PLANILHA PADRÃO DE PROPOSTA - FORNECIMENTO DE SERVIÇO DE TERRAPLANAGEM
A2: Cliente: | B2: RONMA
A3: CNPJ: | B3: 05.635.205/0001-67
A4: Obra: | B4: A. F. EMPREENDIMENTOS IMOBILIARIOS LTDA EPP
A5: Local: | B5: CARAPINA, SERRA - ES
A6: FORNECIMENTO DE MÃO DE OBRA E EQUIPAMENTOS PARA SERVIÇO DE TERRAPLANAGEM
A7: Item | B7: Descrição | C7: Unid. | D7: QUANTIDADE | E7: Preço Unitário (R$) | F7: Valor Total
A8: 1 | B8: PRELIMINARES
A9: 1.1 | B9: Mobilização e desmobilização de equipe e equipamentos. | C9: VB | D9: 2 | E9: 12000 | F9: =D9*E9 -> 24000 | H9: =F9 -> 24000
A10: 1.2 | B10: Equipe de Topografia | C10: VB | D10: 1.5 | E10: 22000 | F10: =D10*E10 -> 33000 | H10: =F10 -> 33000
A11: 2 | B11: LIMPEZA
A12: 2.1 | B12: Limpeza da camada vegetal, incluindo fornecimento de máquinas em perfeito estado de conservação, juntamente com seus respectivos operadores. (Camada de até 20 cm). | C12: M2 | D12: 13321.1 | E12: 1.32 | F12: =D12*E12 -> 17583.852 | H12: =F12 -> 17583.852
A13: 2.2 | B13: Carga / Descarga e Transporte da camada vegetal para bota fora licenciado (com documentação) incluindo fornecimento de caminhões e máquinas em perfeito estado de conservação, juntamente com seus respectivos motoristas e operadores. DMT ATE 1 KM | C13: M3 | D13: =D12*0.3 -> 3996.33 | E13: 6.68 | F13: =D13*E13 -> 26695.484 | G13: 6.68 | H13: =G13*D13 -> 26695.484
A14: 2.3 | B14: Destocamento de árvores com diâmetro > 30 cm, com Escavadeira Hidraúlica e com destinação dentro da própria obra. DMT ATE 1 KM (QUANTITATIVO ESTIPULADO SENDO NECESSÁRIO REALIZAÇÃO DE LEVANTAMENTO PARA CONFIRMAÇÃO) | C14: Unid. | D14: 100 | E14: 53.24 | F14: =D14*E14 -> 5324 | H14: =F14 -> 5324
A15: 3 | B15: ESCAVAÇÃO, CARGA / DESCARGA E TRANSPORTE
A16: 3.1 | B16: Escavação mecânica, Carga e Transporte de material de 1ª categoria e máquinas em perfeito estado de conservação, juntamente com seus respectivos operadores e motoristas. DMT ATE 1 KM. | C16: M3 | D16: 12981.27 | E16: 6.68 | F16: =D16*E16 -> 86714.884 | G16: 6.68 | H16: =G16*D16 -> 86714.884
A17: 4 | B17: ATERRO E COMPACTAÇÃO
A18: 4.1 | B18: Aterro, Espalhamento, Tratamento e Compactação do solo de material de 1ª categoria a 100% procto normal conforme normas vigentes, incluindo fornecimento de máquinas em perfeito estado de conservação, juntamente com seus respectivos operadores. | C18: M3 | D18: 12981.27 | E18: 10.77 | F18: =D18*E18 -> 139808.28 | G18: 7.99 | H18: =G18*D18 -> 103720.35
A19: 4.2 | B19: Nivelamento e Regularização final da área OBS.: Material a ser definido | C19: M3 | D19: 0 | E19: 2.85 | F19: =D19*E19 -> 0
A20: PRAZO PARA EXECUÇÃO: 45 DIAS TRABALHADOS | E20: VALOR TOTAL DO SERVIÇO: | F20: =SUM(F9:F19) -> 333126.5 | H20: =SUM(H9:I18) -> 297038.57 | I20: =H20-F20 -> -36087.931
A22: INFORMAÇÕES DE FATURAMENTO
A23: (OS PERCENTUAIS INFORMADOS DEVEM SEMPRE RESPEITAR AS LEGISLAÇÕES NACIONAIS, ESTADUAIS E MUNICIPAIS PERTINENTES)
A24: A | B24: FATURAMENTO DE PRESTAÇÃO DE SERVIÇOS (MÃO DE OBRA) | C24: 0.15 | D24: =F20*C24 -> 49968.975
A25: B | B25: FATURAMENTO DE EQUIPAMENTOS | C25: 0.85 | D25: =F20*C25 -> 283157.52
B26: PRAZOS (considerando a partir do início dos serviços):
A27: A.1 | B27: Mobilização de equipe e equipamentos. | C27: IMEDIATO MEDIANTE ACEITE DA PROPOSTA
A28: A.2 | B28: Execução dos serviços, considerando áreas 100% liberadas. | C28: 45 DIAS APÓS ACEITE DA PROPOSTA (SEM INTERVENÇÕES TIPO CHUVA)
A30: CHECK LIST TÉCNICO | F30: CAMPO PARA CONFIRMAÇÃO CONTRATADA
A31: 1 | B31: Fornecimento de equipe que atenda o cronograma a ser apresentado no início da obra de modo a não atrasar o andamento dos serviços.
A32: 2 | B32: Mobilização e Desmobilização de todos equipamentos envolvidos na operação necessários para execução do serviço, incluindo seus respectivos motoristas e operadores (02 Escavadeiras Hidráulicas, 01 Motoniveladora, 01 Caminhão Pipa, 02 Rolo Compactador Pé de carneiro, 01 Trator Agrícola com Grade ou qualquer outro que seja necessário para execução do serviço, 05 Caminhões Caçamba Truck, 01 Caminhão Prancha, 01 Automóvel Apoio).
A33: 3 | B33: Fornecimento de Equipe de Topografia para suas respectivas marcações de greide de Terraplenagem e Paviemtação e quaisquer outras atividades que forem de responsabilidade da mesma POR CONTA DA CONTRATADA, laboratório para acompanhamento e verificação do grau de compactação das camadas , entre outros, serão fornecidos PELA CONTRATANTE. Os projetos executivos e detalhes/orientações, serão fornecidos pela CONTRATANTE.
A34: 4 | B34: O critério de medições : • Mediante Levantamento Topográfico Mensal
A35: 5 | B35: O critério de Faturamento : • Emissão de Nota Fiscal e Boleto vencimento 10 Dias após emissão
A36: 6 | B36: O critério de execução : • Caso seja preciso quaisquer outros tipos de atividades para execução dos serviços seja interno ou externo, serão cobrados hora equipamentos em medições. • Quantitativos acima descritos podendo variar mediante levantamento topografico, caso haja alterações serão acrescidos ou descrescidas em medições.

Sheet Dados do Contrato  
A2: Dados do Projeto
B3: M³ In Situ | C3: M³ Empolado | D3: 1.36 | F3: Inicio | G3: Final
A4: Volume de Escavação Total | B4: 12981.27 | C4: =B4*D3 -> 17654.527 | E4: Prazo para Executar | F4: 46118 | G4: 46142 | H4: =NETWORKDAYS.INTL(F4,G4,1,) -> 19
A5: Volume de Escavação Local 01 | B5: 0 | C5: =B5*D3 -> 0 | E5: Dias Uteis no Mês | F5: 46118 | G5: 46142 | H5: 20 | I5: 46118 | J5: 46142 | K5: =NETWORKDAYS.INTL(I5,J5,1,) -> 19
A6: Volume de Escavação Local 02 | B6: 0 | C6: =B6*D3 -> 0 | E6: Total de dias Uteis do Contrato | H6: 22
A7: Volume de Aterro | B7: 12981.27 | C7: =B7*D7 -> 12981.27 | D7: =B4/B7 -> 1 | E7: Prazo em Meses do contrato | F7: =J16/F9 -> 0.20613043 | G7: =H6*F7 -> 4.5348695
A8: Volume de Bota Fora | B8: 0 | C8: =B8*D3 -> 0 | E8: Horas Trabalhadas Por Dia | F8: 8
B9: =SUM(B7:B8) -> 12981.27 | C9: =SUM(C7:C8) -> 12981.27 | E9: Horas Trabalhadas Por Mes | F9: =H5*F8 -> 160
A10: Total de Viagens do Projeto | E10: Total de Horas do Projeto | F10: =F9*F7 -> 32.980869
F11: =F10/F8 -> 4.1226086
A12: Área do Terreno | B12: 13321.1 | E12: Valor do Diesel Para Orçamento | F12: 5.5
A13: Transporte para Local 01 | B13: =B12*0.3 -> 3996.33 | E13: Custo de Manutenção | F13: 0.1
A16: Prazo em Dias Uteis | F16: Produtividade Por Hora | H16: Total de Horas com essa produção | J16: =B4/J23 -> 32.980869 | N16: MOBI / DESMOBI | O16: 0
A17: Escavação e Carga Com Escavadeira | B17: M³ In Situ | C17: M³ Empolado | F17: Viagens | G17: M³ Empolado | H17: M³ Produzido Dia | I17: Viagens Dia | J17: M³ Hora | N17: =$O$16*D18 -> 0
A18: Escavadeira 312 DL | B18: =$B$4/'[1]Dados Equipamentos '!G5 -> 15.024618 | C18: =$C$4/'[1]Dados Equipamentos '!G5 -> 20.433481 | D18: 0 | E18: Escavadeira 312 DL | F18: 10 | G18: =F18*'Dados Transporte (2)'!$D$6 -> 96 | H18: =G18*F8*D18 -> 0 | I18: =D18*F18*F8 -> 0 | J18: =G18*D18 -> 0 | N18: =$O$16*D19 -> 0
A19: Escavadeira 320DL | B19: =$B$9/'[1]Dados Equipamentos '!I6 -> 9.3903863 | C19: =$C$9/'[1]Dados Equipamentos '!I6 -> 9.3903863 | D19: 1 | E19: Escavadeira 320DL | F19: 16 | G19: =F19*'Dados Transporte (2)'!$D$6 -> 153.6 | H19: =G19*$F$8*D19 -> 1228.8 | I19: =F19*$F$8*D19 -> 128 | J19: =G19*D19 -> 153.6 | N19: =$O$16*D20 -> 0
A20: Escavadeira 336DL | B20: =$B$4/'[1]Dados Equipamentos '!G7 -> 6.0098472 | C20: =$C$4/'[1]Dados Equipamentos '!G7 -> 8.1733922 | D20: 1 | E20: Escavadeira 336DL | F20: 25 | G20: =F20*'Dados Transporte (2)'!$D$6 -> 240 | H20: =G20*$F$8*D20 -> 1920 | I20: =F20*$F$8*D20 -> 200 | J20: =G20*D20 -> 240 | N20: =$O$16*D21 -> 0
A21: Escavadeira 345 GC | B21: =$B$4/'[1]Dados Equipamentos '!G8 -> 5.008206 | C21: =$C$4/'[1]Dados Equipamentos '!G8 -> 6.8111602 | D21: 0 | E21: Escavadeira 345 GC | F21: 30 | G21: =F21*'Dados Transporte (2)'!$D$6 -> 288 | H21: =G21*$F$8*D21 -> 0 | I21: =F21*$F$8*D21 -> 0 | J21: =G21*D21 -> 0 | N21: =$O$16*D22 -> 0
N22: =$O$16*D23 -> 0
A23: Total em Horas para Finalizar o Contrato | D23: 0 | E23: Trator de esteiras (N) | H23: =SUM(H18:H21) -> 3148.8 | I23: =SUM(I18:I21) -> 328 | J23: =SUM(J18:J21) -> 393.6 | N23: =$O$16*D24 -> 0
A24: Escavação e Carga Com Escavadeira | B24: Horas do Material In Situ | C24: Horas do Material Empolado | D24: 0 | E24: Trator de esteiras (T) | N24: =$O$16*D25 -> 0
A25: Escavadeira 312 DL | B25: =$F$8*B18 -> 120.19694 | C25: =$F$8*C18 -> 163.46784 | D25: 1 | E25: Patrol | N25: =$O$16*D26 -> 0
A26: Escavadeira 320DL | B26: =$F$8*B19 -> 75.12309 | C26: =$F$8*C19 -> 75.12309 | D26: 0.5 | E26: Grade | N26: =$O$16*D27 -> 0
A27: Escavadeira 336DL | B27: =$F$8*B20 -> 48.078778 | C27: =$F$8*C20 -> 65.387138 | D27: 2 | E27: Rolo Compactador | N27: =$O$16*D28 -> 0
A28: Escavadeira 345 GC | B28: =$F$8*B21 -> 40.065648 | C28: =$F$8*C21 -> 54.489281 | D28: 0.5 | E28: Caminhão Pipa | N28: =$O$16*D29 -> 0
D29: 1 | E29: Apontador
A30: Prazo em Dias Uteis | D30: 1 | E30: Administrativo | N30: =SUM(N17:N29) -> 0
A31: Limpesa de Terreno | B31: M² | D31: 1 | E31: Topografia
A32: Escavadeira 312 DL | B32: =B12/'[1]Dados Equipamentos '!G19 -> 2.9602444 | D32: 1 | E32: Laboratório
D33: 1 | E33: Alojamento
A34: Total em Horas para Finalizar o Contrato de Limpesa | D34: 1 | E34: Alimentação | G34: ='COMPOSIÇÃO DE PREÇO'!B9 -> 0.75457317
B35: M² | D35: 0 | E35: Vigilancia | G35: ='COMPOSIÇÃO DE PREÇO'!F23 -> 4.9027937
A36: Escavadeira 312 DL | B36: =B32*F8 -> 23.681956 | J36: 210000
J37: =J36/B4 -> 16.177154

Sheet COMPOSIÇÃO DE PREÇO
H2: 1.5
A3: COMPOSIÇÃO DE PREÇOS OBRA RONMA | H3: 2.3 | I3: 13.5 | J3: 1.2 | L3: =I3-F23 -> 8.5972063 | M3: =L3/I3 -> 0.6368301 | N3: =M3-H3 -> -1.6631699
B4: Diesel | C4: Manutenção | D4: Mão de Obra | E4: Indirétos | F4: Total | L4: =H23-I3 -> 6.1580327 | M4: =L4/I3 -> 0.45615057
A5: Limpeza
A6: Escavadeira | B6: =IF('Dados do Contrato '!B13<>0,SUM('CUSTOS EQUIPAMENTOS'!D5+'CUSTOS EQUIPAMENTOS'!D6+'CUSTOS EQUIPAMENTOS'!D7+'CUSTOS EQUIPAMENTOS'!D8)/'Dados do Contrato '!B13,0) -> 2.4510784 | C6: =IF('Dados do Contrato '!B13<>0,SUM('CUSTOS EQUIPAMENTOS'!F5+'CUSTOS EQUIPAMENTOS'!F6+'CUSTOS EQUIPAMENTOS'!F7+'CUSTOS EQUIPAMENTOS'!F8)/'Dados do Contrato '!B13,0) -> 0.70148708 | D6: =IF('Dados do Contrato '!B13<>0,SUM('CUSTOS EQUIPAMENTOS'!H5+'CUSTOS EQUIPAMENTOS'!H6+'CUSTOS EQUIPAMENTOS'!H7+'CUSTOS EQUIPAMENTOS'!H8)/'Dados do Contrato '!B13,0) -> 0.53860308 | E6: ='CUSTOS EQUIPAMENTOS'!J24 -> 0.1135405 | F6: =SUM(B6:E6) -> 3.804709 | G6: ='Dados do Contrato '!$B$13*'COMPOSIÇÃO DE PREÇO'!F6 -> 15204.873 | H6: =F6*$H$3 -> 8.7508308 | I6: ='Dados do Contrato '!$B$13*'COMPOSIÇÃO DE PREÇO'!H6 -> 34971.208 | J6: =H6*$J$3 -> 10.500997 | K6: =J6*'Dados do Contrato '!$B$13 -> 41965.449 | L6: =I6/I23 -> 0.19806921 | M6: =G6/$I$23 -> 0.08611705 | N6: =I6-G6 -> 19766.335 | O6: =N6/$I$23 -> 0.11195216 | P6: 0.06 | Q6: =H6*P6 -> 0.52504985 | R6: =3.85-Q6 -> 3.3249502 | S6: =F6*O7 -> 7.6094181
O7: 2
A8: Escavação e Carga
A9: Escavadeira | B9: =IF('Dados do Contrato '!B4<>0,SUM('CUSTOS EQUIPAMENTOS'!D5+'CUSTOS EQUIPAMENTOS'!D6+'CUSTOS EQUIPAMENTOS'!D7+'CUSTOS EQUIPAMENTOS'!D8)/'Dados do Contrato '!B4,0) -> 0.75457317 | C9: =IF('Dados do Contrato '!B4<>0,SUM('CUSTOS EQUIPAMENTOS'!F5+'CUSTOS EQUIPAMENTOS'!F6+'CUSTOS EQUIPAMENTOS'!F7+'CUSTOS EQUIPAMENTOS'!F8)/'Dados do Contrato '!B4,0) -> 0.21595528 | D9: =IF('Dados do Contrato '!B4<>0,SUM('CUSTOS EQUIPAMENTOS'!H5+'CUSTOS EQUIPAMENTOS'!H6+'CUSTOS EQUIPAMENTOS'!H7+'CUSTOS EQUIPAMENTOS'!H8)/'Dados do Contrato '!B4,0) -> 0.16581087 | E9: ='CUSTOS EQUIPAMENTOS'!J24 -> 0.1135405 | F9: =SUM(B9:E9) -> 1.2498798 | G9: ='Dados do Contrato '!$B$4*'COMPOSIÇÃO DE PREÇO'!F9 -> 16225.028 | H9: 3.48 | I9: ='Dados do Contrato '!$B$4*'COMPOSIÇÃO DE PREÇO'!H9 -> 45174.82 | J9: =H9*$J$3 -> 4.176 | K9: =J9*'Dados do Contrato '!$B$4 -> 54209.784 | L9: =I9/I23 -> 0.25586022 | M9: =G9/$I$23 -> 0.091894981 | N9: =I9-G9 -> 28949.792 | O9: =N9/$I$23 -> 0.16396524 | P9: 0.06 | Q9: =H9*P9 -> 0.2088 | R9: =3.85-Q9 -> 3.6412 | S9: =F9*O7 -> 2.4997597
A10: Transporte | I10: ='Dados do Contrato '!$B$4*'COMPOSIÇÃO DE PREÇO'!H10 -> 0 | J10: =H10*$J$3 -> 0 | K10: =J10*'Dados do Contrato '!$B$4 -> 0 | N10: =I10-G10 -> 0
A11: Caminhões Escavação Aterro | F11: ='Dados Transporte (2)'!C11 -> 1.815 | G11: ='Dados do Contrato '!C4*'COMPOSIÇÃO DE PREÇO'!F11 -> 32042.967 | H11: 3.2 | I11: ='Dados do Contrato '!$B$4*'COMPOSIÇÃO DE PREÇO'!H11 -> 41540.064 | J11: =H11*$J$3 -> 3.84 | K11: =J11*'Dados do Contrato '!$B$4 -> 49848.077 | L11: =I11/I23 -> 0.23527377 | M11: =G11/$I$23 -> 0.1814843 | N11: =I11-G11 -> 9497.0971 | O11: =N11/$I$23 -> 0.053789465
A12: Caminhões Bota Fora | F12: 3.2 | G12: ='Dados do Contrato '!B13*'COMPOSIÇÃO DE PREÇO'!F12 -> 12788.256 | I12: ='Dados do Contrato '!$B$13*'COMPOSIÇÃO DE PREÇO'!H12 -> 0 | J12: =H12*$J$3 -> 0 | K12: =J12*'Dados do Contrato '!$B$4 -> 0
A13: Total | G13: =SUM(G11:G12) -> 44831.223 | I13: ='Dados do Contrato '!$B$4*'COMPOSIÇÃO DE PREÇO'!H13 -> 0 | J13: =H13*$J$3 -> 0 | K13: =J13*'Dados do Contrato '!$B$4 -> 0
A14: Aterro Compactado
A15: Espalhamento / Tratamento
A16: Trator de esteiras (T) | B16: =IF('Dados do Contrato '!B4<>0,SUM('CUSTOS EQUIPAMENTOS'!D9+'CUSTOS EQUIPAMENTOS'!D10)/'Dados do Contrato '!B4,0) -> 0 | C16: =IF('Dados do Contrato '!B4<>0,SUM('CUSTOS EQUIPAMENTOS'!F9+'CUSTOS EQUIPAMENTOS'!F10)/'Dados do Contrato '!$B$4,0) -> 0 | D16: =IF('Dados do Contrato '!B4<>0,SUM('CUSTOS EQUIPAMENTOS'!H9+'CUSTOS EQUIPAMENTOS'!H10)/'Dados do Contrato '!B4,0) -> 0 | E16: ='CUSTOS EQUIPAMENTOS'!K9 -> 0 | F16: =SUM(B16:E16) -> 0 | G16: ='Dados do Contrato '!$B$7*'COMPOSIÇÃO DE PREÇO'!F16 -> 0 | H16: =F16*$H$3 -> 0 | I16: ='Dados do Contrato '!$B$4*'COMPOSIÇÃO DE PREÇO'!H16 -> 0 | J16: =H16*$J$3 -> 0 | K16: =J16*'Dados do Contrato '!$B$4 -> 0 | L16: =I16/I23 -> 0 | M16: =G16/$I$23 -> 0 | N16: =I16-G16 -> 0 | O16: =N16/$I$23 -> 0 | P16: 6
A17: Motoniveladora | B17: =IF('Dados do Contrato '!B4<>0,'CUSTOS EQUIPAMENTOS'!D11/'Dados do Contrato '!B4,0) -> 0.23755081 | C17: =IF('Dados do Contrato '!B4<>0,'CUSTOS EQUIPAMENTOS'!F11/'Dados do Contrato '!$B$4,0) -> 0.099085366 | D17: =IF('Dados do Contrato '!B4<>0,'CUSTOS EQUIPAMENTOS'!H11/'Dados do Contrato '!$B$4,0) -> 0.062847668 | E17: ='CUSTOS EQUIPAMENTOS'!K11 -> 0.1135405 | F17: =SUM(B17:E17) -> 0.51302435 | G17: ='Dados do Contrato '!$B$7*'COMPOSIÇÃO DE PREÇO'!F17 -> 6659.7076 | H17: =F17*$H$3 -> 1.179956 | I17: ='Dados do Contrato '!$B$7*'COMPOSIÇÃO DE PREÇO'!H17 -> 15317.328 | J17: =H17*$J$3 -> 1.4159472 | K17: =J17*'Dados do Contrato '!$B$7 -> 18380.793 | L17: =I17/I23 -> 0.086753968 | M17: =G17/$I$23 -> 0.037719117 | N17: =I17-G17 -> 8657.6199 | O17: =N17/$I$23 -> 0.049034851 | P17: 4
A18: Trator com Grade | B18: =IF('Dados do Contrato '!B4<>0,'CUSTOS EQUIPAMENTOS'!D12/'Dados do Contrato '!$B$4,0) -> 0.10480183 | C18: =IF('Dados do Contrato '!B4<>0,'CUSTOS EQUIPAMENTOS'!F12/'Dados do Contrato '!$B$4,0) -> 0.022865854 | D18: =IF('Dados do Contrato '!B4<>0,'CUSTOS EQUIPAMENTOS'!H12/'Dados do Contrato '!$B$4,0) -> 0.026743688 | E18: ='CUSTOS EQUIPAMENTOS'!K12 -> 0.1135405 | F18: =SUM(B18:E18) -> 0.26795188 | G18: ='Dados do Contrato '!$B$7*'COMPOSIÇÃO DE PREÇO'!F18 -> 3478.3556 | H18: =F18*$H$3 -> 0.61628931 | I18: ='Dados do Contrato '!$B$7*'COMPOSIÇÃO DE PREÇO'!H18 -> 8000.218 | J18: =H18*$J$3 -> 0.73954718 | K18: =J18*'Dados do Contrato '!$B$7 -> 9600.2616 | L18: =I18/$I$23 -> 0.045311472 | M18: =G18/$I$23 -> 0.01970064 | N18: =I18-G18 -> 4521.8623 | O18: =N18/$I$23 -> 0.025610832 | P18: 3
A19: Caminhão Pipa | B19: =IF('Dados do Contrato '!B4<>0,'CUSTOS EQUIPAMENTOS'!D14/'Dados do Contrato '!$B$4,0) -> 0.055894309 | C19: =IF('Dados do Contrato '!B4<>0,'CUSTOS EQUIPAMENTOS'!F14/'Dados do Contrato '!$B$4,0) -> 0.043191057 | D19: =IF('Dados do Contrato '!B4<>0,'CUSTOS EQUIPAMENTOS'!H14/'Dados do Contrato '!$B$4,0) -> 0.026743688 | E19: ='CUSTOS EQUIPAMENTOS'!K14 -> 0.1135405 | F19: =SUM(B19:E19) -> 0.23936956 | G19: ='Dados do Contrato '!$B$7*'COMPOSIÇÃO DE PREÇO'!F19 -> 3107.3209 | H19: =F19*$H$3 -> 0.55054998 | I19: ='Dados do Contrato '!$B$7*'COMPOSIÇÃO DE PREÇO'!H19 -> 7146.838 | J19: =H19*$J$3 -> 0.66065998 | K19: =J19*'Dados do Contrato '!$B$7 -> 8576.2056 | L19: =I19/$I$23 -> 0.040478116 | M19: =G19/$I$23 -> 0.017599181 | N19: =I19-G19 -> 4039.5171 | O19: =N19/$I$23 -> 0.022878935 | P19: 4
A20: Compactação de Solo
A21: Rolo | B21: =IF('Dados do Contrato '!B4<>0,'CUSTOS EQUIPAMENTOS'!D13/'Dados do Contrato '!$B$4,0) -> 0.41920732 | C21: =IF('Dados do Contrato '!B4<>0,'CUSTOS EQUIPAMENTOS'!F13/'Dados do Contrato '!$B$4,0) -> 0.17784553 | D21: =IF('Dados do Contrato '!B4<>0,'CUSTOS EQUIPAMENTOS'!H13/'Dados do Contrato '!$B$4,0) -> 0.10697475 | E21: ='CUSTOS EQUIPAMENTOS'!K13 -> 0.1135405 | F21: =SUM(B21:E21) -> 0.8175681 | G21: ='Dados do Contrato '!$B$7*'COMPOSIÇÃO DE PREÇO'!F21 -> 10613.072 | H21: =F21*$H$3 -> 1.8804066 | I21: ='Dados do Contrato '!$B$7*'COMPOSIÇÃO DE PREÇO'!H21 -> 24410.066 | J21: =H21*$J$3 -> 2.256488 | K21: =J21*'Dados do Contrato '!$B$7 -> 29292.08 | L21: =I21/$I$23 -> 0.13825324 | M21: =G21/$I$23 -> 0.060110103 | N21: =I21-G21 -> 13796.994 | O21: =N21/$I$23 -> 0.078143134 | P21: 1
A22: Total
E23: Custo Total do Projeto | F23: =SUM(F21,F16:F19,F11,F9) -> 4.9027937 | G23: =SUM(G21,G16:G19,G13,G9,G6) -> 100119.58 | H23: =SUM(H6:H21) -> 19.658033 | I23: =SUM(I6:I22) -> 176560.54 | J23: =SUM(J9:J21) -> 13.088642 | K23: =SUM(K6:K22) -> 211872.65 | L23: =I23-G23 -> 76440.961 | M23: =G23/$I$23 -> 0.56705524
B24: =SUM(B6:B21) -> 4.0231058 | C24: =SUM(C6:C21) -> 1.2604302 | D24: =SUM(D6:D21) -> 0.92772375 | E24: =SUM(E6:E21) -> 0.68124303 | F24: =SUM(F6:F21) -> 11.907503
E25: Preço de: | H25: =H23 -> 19.658033 | J25: =SUM(H9:H11) -> 6.68
E26: Orçamento Apresentado | G26: =Terraplenagem!F18 -> 564753.06 | J26: =SUM(H17:H21) -> 4.2272019
J27: =SUM(J25:J26) -> 10.907202
E28: Lucro Estimado | G28: =G26-G25-G23 -> 464633.48
E29: Imposto sobre Lucro | F29: 0.3825 | G29: =G28*F29 -> 177722.31
E31: Lucro Liquido | G31: =G28-G29 -> 286911.17 | H31: =IF(G26<>0,G31/G26,0) -> 0.50802943
E32: Preço de : | H32: =J23 -> 13.088642
E33: Orçamento Apresentado | G33: =K23 -> 211872.65
E35: Lucro Estimado | G35: =G33-G23 -> 111753.07
E36: Imposto sobre Lucro | F36: 0.3825 | G36: =G35*F36 -> 42745.549
E38: Lucro Liquido | G38: =G35-G36 -> 69007.52 | H38: =IF(G33<>0,G38/G33,0) -> 0.32570283

Sheet CUSTOS EQUIPAMENTOS
D2: =D6/'Dados do Contrato '!C4 -> 0.17466972
A3: Descrição | B3: Quant. | C3: Custo H Diesel | D3: Total Diesel | E3: Custo H Manutenção | F3: Total Manutenção | G3: Custo H.H. | H3: Total H. Homem | I3: Custos H Indirétos | J3: Total Indirétos | K3: Coluna11 | L3: Total de Custos | M3: Total de Custo Mensal
C4: Custo Díesel | E4: Custo Manutenção | G4: Custo H.H. | I4: Custos Indirétos | M4: Total de Custo Mensal
A5: Escavadeira 312 DL | B5: =IF('Dados do Contrato '!D18>0,'Dados do Contrato '!D18,0) -> 0 | C5: ='MÉDIA CONSUMO '!E5 -> 66 | D5: =C5*'Dados do Contrato '!$J$16*B5 -> 0 | E5: 34.5 | F5: =E5*'Dados do Contrato '!$F$10*B5 -> 0 | G5: 32.631579 | H5: =G5*'Dados do Contrato '!$F$10*B5 -> 0 | J5: =I5*B5*'Dados do Contrato '!$F$10 -> 0 | K5: =IF(B5>0,$J$24,0) -> 0 | L5: =J5+H5+F5+D5 -> 0 | M5: =L5/'Dados do Contrato '!$F$7 -> 0
A6: Escavadeira 320DL | B6: =IF('Dados do Contrato '!D19>0,'Dados do Contrato '!D19,0) -> 1 | C6: ='MÉDIA CONSUMO '!E6 -> 93.5 | D6: =C6*'Dados do Contrato '!$J$16*B6 -> 3083.7112 | E6: 37 | F6: =E6*'Dados do Contrato '!$F$10*B6 -> 1220.2921 | G6: 32.631579 | H6: =G6*'Dados do Contrato '!$F$10*B6 -> 1076.2178 | J6: =I6*B6*'Dados do Contrato '!$F$10 -> 0 | K6: =IF(B6>0,$J$24,0) -> 0.1135405 | L6: =J6+H6+F6+D6 -> 5380.2212 | M6: =L6/'Dados do Contrato '!$F$7 -> 26101.053
A7: Escavadeira 336DL | B7: =IF('Dados do Contrato '!D20>0,'Dados do Contrato '!D20,0) -> 1 | C7: ='MÉDIA CONSUMO '!E7 -> 203.5 | D7: =C7*'Dados do Contrato '!$J$16*B7 -> 6711.6068 | E7: 48 | F7: =E7*'Dados do Contrato '!$F$10*B7 -> 1583.0817 | G7: 32.631579 | H7: =G7*'Dados do Contrato '!$F$10*B7 -> 1076.2178 | J7: =I7*B7*'Dados do Contrato '!$F$10 -> 0 | K7: =IF(B7>0,$J$24,0) -> 0.1135405 | L7: =J7+H7+F7+D7 -> 9370.9064 | M7: =L7/'Dados do Contrato '!$F$7 -> 45461.053
A8: Escavadeira 345 GC | B8: =IF('Dados do Contrato '!D21>0,'Dados do Contrato '!D21,0) -> 0 | C8: ='MÉDIA CONSUMO '!E8 -> 214.5 | D8: =C8*'Dados do Contrato '!$J$16*B8 -> 0 | E8: 53 | F8: =E8*'Dados do Contrato '!$F$10*B8 -> 0 | G8: 32.631579 | H8: =G8*'Dados do Contrato '!$F$10*B8 -> 0 | J8: =I8*B8*'Dados do Contrato '!$F$10 -> 0 | K8: =IF(B8>0,$J$24,0) -> 0 | L8: =J8+H8+F8+D8 -> 0 | M8: =L8/'Dados do Contrato '!$F$7 -> 0
A9: Trator de esteiras (N) | B9: =IF('Dados do Contrato '!D23>0,'Dados do Contrato '!D23,0) -> 0 | C9: ='MÉDIA CONSUMO '!H9 -> 154 | D9: =C9*'Dados do Contrato '!$J$16*B9 -> 0 | E9: 43.5 | F9: =E9*'Dados do Contrato '!$F$10*B9 -> 0 | G9: 24.736842 | H9: =G9*'Dados do Contrato '!$F$10*B9 -> 0 | J9: =I9*B9*'Dados do Contrato '!$F$10 -> 0 | K9: =IF(B9>0,$J$24,0) -> 0 | L9: =J9+H9+F9+D9 -> 0 | M9: =L9/'Dados do Contrato '!$F$7 -> 0
A10: Trator de esteiras (T) | B10: =IF('Dados do Contrato '!D24>0,'Dados do Contrato '!D24,0) -> 0 | C10: ='MÉDIA CONSUMO '!E10 -> 214.5 | D10: =C10*'Dados do Contrato '!$J$16*B10 -> 0 | E10: 43.5 | F10: =E10*'Dados do Contrato '!$F$10*B10 -> 0 | G10: 24.736842 | H10: =G10*'Dados do Contrato '!$F$10*B10 -> 0 | J10: =I10*B10*'Dados do Contrato '!$F$10 -> 0 | K10: =IF(B10>0,$J$24,0) -> 0 | L10: =J10+H10+F10+D10 -> 0 | M10: =L10/'Dados do Contrato '!$F$7 -> 0
A11: Patrol | B11: =IF('Dados do Contrato '!D25<>0,'Dados do Contrato '!D25,0) -> 1 | C11: ='MÉDIA CONSUMO '!E11 -> 93.5 | D11: =C11*'Dados do Contrato '!$J$16*B11 -> 3083.7112 | E11: 39 | F11: =E11*'Dados do Contrato '!$F$10*B11 -> 1286.2539 | G11: 24.736842 | H11: =G11*'Dados do Contrato '!$F$10*B11 -> 815.84255 | J11: =I11*B11*'Dados do Contrato '!$F$10 -> 0 | K11: =IF(B11>0,$J$24,0) -> 0.1135405 | L11: =J11+H11+F11+D11 -> 5185.8077 | M11: =L11/'Dados do Contrato '!$F$7 -> 25157.895
A12: Grade | B12: =IF('Dados do Contrato '!D26>0,'Dados do Contrato '!D26,0) -> 0.5 | C12: ='MÉDIA CONSUMO '!E12 -> 82.5 | D12: =C12*'Dados do Contrato '!$J$16*B12 -> 1360.4608 | E12: 18 | F12: =E12*'Dados do Contrato '!$F$10*B12 -> 296.82782 | G12: 21.052632 | H12: =G12*'Dados do Contrato '!$F$10*B12 -> 347.16704 | J12: =I12*B12*'Dados do Contrato '!$F$10 -> 0 | K12: =IF(B12>0,$J$24,0) -> 0.1135405 | L12: =J12+H12+F12+D12 -> 2004.4557 | M12: =L12/'Dados do Contrato '!$F$7 -> 9724.2105
A13: Rolo Compactador | B13: =IF('Dados do Contrato '!D27>0,'Dados do Contrato '!D27,0) -> 2 | C13: ='MÉDIA CONSUMO '!E13 -> 82.5 | D13: =C13*'Dados do Contrato '!$J$16*B13 -> 5441.8434 | E13: 35 | F13: =E13*'Dados do Contrato '!$F$10*B13 -> 2308.6608 | G13: 21.052632 | H13: =G13*'Dados do Contrato '!$F$10*B13 -> 1388.6682 | J13: =I13*B13*'Dados do Contrato '!$F$10 -> 0 | K13: =IF(B13>0,$J$24,0) -> 0.1135405 | L13: =J13+H13+F13+D13 -> 9139.1724 | M13: =L13/'Dados do Contrato '!$F$7 -> 44336.842
A14: Caminhão Pipa | B14: =IF('Dados do Contrato '!D28>0,'Dados do Contrato '!D28,0) -> 0.5 | C14: ='MÉDIA CONSUMO '!E14 -> 44 | D14: =C14*'Dados do Contrato '!$J$16*B14 -> 725.57912 | E14: 34 | F14: =E14*'Dados do Contrato '!$F$10*B14 -> 560.67477 | G14: 21.052632 | H14: =G14*'Dados do Contrato '!$F$10*B14 -> 347.16704 | J14: =I14*B14*'Dados do Contrato '!$F$10 -> 0 | K14: =IF(B14>0,$J$24,0) -> 0.1135405 | L14: =J14+H14+F14+D14 -> 1633.4209 | M14: =L14/'Dados do Contrato '!$F$7 -> 7924.2105
A15: Apontador | B15: =IF('Dados do Contrato '!D29>0,'Dados do Contrato '!D29,0) -> 1 | F15: =E15*'Dados do Contrato '!$F$10*B15 -> 0 | G15: 21.052632 | H15: =G15*'Dados do Contrato '!$F$10*B15 -> 694.33408 | J15: =I15*B15*'Dados do Contrato '!$F$10 -> 0 | L15: =J15+H15+F15+D15 -> 694.33408 | M15: =L15/'Dados do Contrato '!$F$7 -> 3368.4211
A16: Administrativo | B16: =IF('Dados do Contrato '!D30>0,'Dados do Contrato '!D30,0) -> 1 | F16: =E16*'Dados do Contrato '!$F$10*B16 -> 0 | G16: 24.736842 | H16: =G16*'Dados do Contrato '!$F$10*B16 -> 815.84255 | J16: =I16*B16*'Dados do Contrato '!$F$10 -> 0 | L16: =J16+H16+F16+D16 -> 815.84255 | M16: =L16/'Dados do Contrato '!$F$7 -> 3957.8947
A17: Topografia | B17: =IF('Dados do Contrato '!D31>0,'Dados do Contrato '!D31,0) -> 1 | F17: =E17*'Dados do Contrato '!$F$10*B17 -> 0 | H17: =G17*'Dados do Contrato '!$F$10*B17 -> 0 | I17: 88.888889 | J17: =I17*'Dados do Contrato '!$F$10*B17 -> 2931.6328 | L17: =J17+H17+F17+D17 -> 2931.6328 | M17: =L17/'Dados do Contrato '!$F$7 -> 14222.222
A18: Laboratório | B18: =IF('Dados do Contrato '!D32>0,'Dados do Contrato '!D32,0) -> 1 | F18: =E18*'Dados do Contrato '!$F$10*B18 -> 0 | H18: =G18*'Dados do Contrato '!$F$10*B18 -> 0 | I18: 88.888889 | J18: =I18*'Dados do Contrato '!$F$10*B18 -> 2931.6328 | L18: =J18+H18+F18+D18 -> 2931.6328 | M18: =L18/'Dados do Contrato '!$F$7 -> 14222.222
A19: Alojamento | B19: =IF('Dados do Contrato '!D33>0,'Dados do Contrato '!D33,0) -> 1 | F19: =E19*'Dados do Contrato '!$F$10*B19 -> 0 | H19: =G19*'Dados do Contrato '!$F$10*B19 -> 0 | I19: 46.111111 | J19: =I19*'Dados do Contrato '!$F$10*B19 -> 1520.7845 | L19: =J19+H19+F19+D19 -> 1520.7845 | M19: =L19/'Dados do Contrato '!$F$7 -> 7377.7778
A20: Alimentação | B20: =IF('Dados do Contrato '!D34>0,'Dados do Contrato '!D34,0) -> 1 | F20: =E20*'Dados do Contrato '!$F$10*B20 -> 0 | H20: =G20*'Dados do Contrato '!$F$10*B20 -> 0 | I20: =(B22*40*30)/180 -> 80 | J20: =I20*'Dados do Contrato '!$F$10*B20 -> 2638.4695 | L20: =J20+H20+F20+D20 -> 2638.4695 | M20: =L20/'Dados do Contrato '!$F$7 -> 12800
A21: Vigilancia | B21: =IF('Dados do Contrato '!D35>0,'Dados do Contrato '!D35,0) -> 0 | F21: =E21*'Dados do Contrato '!$F$10*B21 -> 0 | H21: =G21*'Dados do Contrato '!$F$10*B21 -> 0 | I21: 138.88889 | J21: =I21*'Dados do Contrato '!$F$10*B21 -> 0 | L21: =J21+H21+F21+D21 -> 0 | M21: =L21/'Dados do Contrato '!$F$7 -> 0
B22: =SUM(B5:B21) -> 12 | D22: =SUM(D5:D21) -> 20406.913 | J22: =SUM(J17:J21) -> 10022.52 | L22: =SUM(L5:L21) -> 44246.68 | M22: =SUM(M5:M21) -> 214653.8
J23: =IF(J22<>0,J22/'Dados do Contrato '!C4,0) -> 0.56770252 | K23: =IF(J22<>0,J22/'Dados do Contrato '!B13,0) -> 2.5079309
J24: =J23/5 -> 0.1135405 | K24: =K23/5 -> 0.50158619
A25: Escavadeira 312 DL | B25: 0 | C25: 66 | E25: 0
A26: Escavadeira 320DL | B26: 1 | C26: 93.5 | D26: 15101 | E26: 12343.461 | F26: =E26-D26 -> -2757.5391 | J26: =J23/5 -> 0.1135405
A27: Escavadeira 336DL | B27: 0 | C27: 203.5 | E27: 0 | F27: =E27-D27 -> 0
A28: Escavadeira 345 GC | B28: 0 | C28: 214.5 | E28: 0 | F28: =E28-D28 -> 0
A29: Trator de esteiras (N) | B29: 1 | C29: 154 | E29: 0 | F29: =E29-D29 -> 0
A30: Trator de esteiras (T) | B30: 0 | C30: 214.5 | D30: 4046.26 | E30: 14158.676 | F30: =E30-D30 -> 10112.416 | H30: 16000 | I30: =H30/'Dados do Contrato '!F9 -> 100
A31: Patrol | B31: 1 | C31: 93.5 | D31: 10577.84 | E31: 6171.7305 | F31: =E31-D31 -> -4406.1095
A32: Grade | B32: 1 | C32: 82.5 | D32: 4482.65 | E32: 5445.6445 | F32: =E32-D32 -> 962.99453
A33: Rolo Compactador | B33: 2 | C33: 154 | D33: 19314 | E33: 20330.406 | F33: =E33-D33 -> 1016.4062 | I33: =25000*25 -> 625000
A34: Caminhão Pipa | B34: 1 | C34: 44 | D34: 1541.18 | E34: 3041.28 | F34: =E34-D34 -> 1500.1
D35: =SUM(D25:D34) -> 55062.93 | E35: =SUM(E25:E34) -> 61491.198
E36: =E35-D35 -> 6428.268

Sheet Dados Transporte  (2)
A3: DMT 2KM
A4: Fator de Empolamento Material | B4: 0.36
B5: M³ In Sito | C5: Perca de Volume | D5: M³ Empolado
A6: Volume Transportado por viagem | B6: 15 | C6: =B6*B4 -> 5.4 | D6: =B6-C6 -> 9.6
A8: Valor Conbinado do Frete | C8: 1.65 | D8: ='Dados do Contrato '!C4*'Dados Transporte (2)'!C8 -> 29129.97 | G8: ='[1]Dados do Contrato '!B5 -> 0 | H8: =C8*'[1]Dados do Contrato '!C4 -> 442186.51
A9: Fator de Empolamento | B9: 0.1 | C9: =C8*B9 -> 0.165 | D9: =C9*'Dados do Contrato '!C4 -> 2912.997 | E9: =D7*B9 -> 0 | G9: =B9*'[1]Dados do Contrato '!B5 -> 0
A10: Perca no Carregamento | B10: 0 | C10: =C8*B10 -> 0 | D10: =C10*'Dados do Contrato '!C4 -> 0 | E10: =D7*B10 -> 0 | G10: =B10*'[1]Dados do Contrato '!B6 -> 0 | H10: =36-60 -> -24
B11: =SUM(B9:B10) -> 0.1 | C11: =SUM(C8:C10) -> 1.815 | D11: =SUM(D8:D10) -> 32042.967 | E11: =SUM(E9:E10,D7) -> 0 | F11: 40362.81 | G11: =D11-F11 -> -8319.8431
D12: =D11/'Dados do Contrato '!C4 -> 1.815 | F12: =D11-F11 -> -8319.8431 | G12: =G11*C8 -> -13727.741
B13: =C8*B11 -> 0.165 | F13: =F12/D11 -> -0.25964647
A15: DMT 12KM - BOTA FORA
A16: Fator de Empolamento Material | B16: 0.36
B17: M³ In Sito | C17: Perca de Volume | D17: M³ Empolado | F17: =C23*D18 -> 420 | G17: =F17-F18 -> 120
A18: Volume Transportado por viagem | B18: 15 | C18: =B18*B16 -> 5.4 | D18: =B18-C18 -> 9.6 | F18: 300 | G18: VALOR VIAGEM
F19: =F18/D18 -> 31.25
A20: Valor Conbinado do Frete | C20: =F19 -> 31.25 | D20: ='Dados do Contrato '!B13*'Dados Transporte (2)'!C20 -> 124885.31 | G20: ='[1]Dados do Contrato '!B17 -> M³ In Situ | H20: =C20*'[1]Dados do Contrato '!C16 -> 0
A21: Fator de Empolamento | B21: 0.1 | C21: =C20*B21 -> 3.125 | D21: =C21*'Dados do Contrato '!B13 -> 12488.531 | E21: =D19*B21 -> 0 | G21: =B21*'[1]Dados do Contrato '!B17 -> #VALUE!
A22: Perca no Carregamento | B22: 0.3 | C22: =C20*B22 -> 9.375 | D22: =C22*'Dados do Contrato '!B13 -> 37465.594 | E22: =D19*B22 -> 0 | G22: =B22*'[1]Dados do Contrato '!B18 -> 68.421115 | H22: =36-60 -> -24
B23: =SUM(B21:B22) -> 0.4 | C23: =SUM(C20:C22) -> 43.75 | D23: =SUM(D20:D22) -> 174839.44 | E23: =SUM(E21:E22,D19) -> 0 | F23: 40362.81 | G23: =D23-F23 -> 134476.63
D24: =D23/'Dados do Contrato '!B13 -> 43.75 | F24: =D23-F23 -> 134476.63 | G24: =G23*C20 -> 4202394.6
B25: =C20*B23 -> 12.5 | F25: =F24/D23 -> 0.76914356
B27: =H10/'[1]Dados do Contrato '!C4 -> -8.9554972e-05
A28: DMT 8KM
A29: Fator de Empolamento Material | B29: 0.36
B30: M³ In Sito | C30: Perca de Volume | D30: M³ Empolado
A31: Volume Transportado por viagem | B31: 15 | C31: =B31*B29 -> 5.4 | D31: =B31-C31 -> 9.6 | F31: 0.3 | H31: =D32*F31 -> 5484.666 | I31: =SUM(D32,H31:H32) -> 32907.996
D32: 18282.22 | F32: 0.5 | H32: =D32*F32 -> 9141.11 | J32: =D32*12 -> 219386.64
A33: Valor Conbinado do Frete | C33: 0 | D33: =C33*'[1]Dados do Contrato '!$B$6 -> 0 | G33: ='[1]Dados do Contrato '!$B$6 -> 0 | J33: =J32*F32 -> 109693.32
A34: Fator de Empolamento | B34: 0.36 | C34: =C33*B34 -> 0 | D34: =C34*'[1]Dados do Contrato '!$B$6 -> 0 | G34: =B34*'[1]Dados do Contrato '!B6 -> 0 | J34: =SUM(J32:J33) -> 329079.96
A35: Perca no Carregamento | B35: 0.14 | C35: =C33*B35 -> 0 | D35: =C35*'[1]Dados do Contrato '!$B$6 -> 0 | G35: =B35*'[1]Dados do Contrato '!B6 -> 0 | J35: =J34/D32 -> 18
B36: =SUM(B34:B35) -> 0.5 | C36: =SUM(C33:C35) -> 0 | D36: =SUM(D33:D35) -> 0 | E36: =C36*D32 -> 0 | G36: =SUM(G33:G35) -> 0 | J36: =J35*F31 -> 5.4
D37: =D36/D32 -> 0 | G37: =G36*C33 -> 0
B38: =C33*B36 -> 0
B41: =36-80 -> -44

Sheet MÉDIA CONSUMO 
B4: Quant. Equipamentos | D4: Média Consumo Hora | E4: Custo ( R$ ) Hora
A5: Escavadeira 312 DL | B5: 1 | C5: 1 | D5: 12 | E5: =D5*C5*'Dados do Contrato '!$F$12 -> 66
A6: Escavadeira 320DL | B6: 1 | C6: 1 | D6: 17 | E6: =D6*C6*'Dados do Contrato '!$F$12 -> 93.5
A7: Escavadeira 336DL | B7: 1 | C7: 1 | D7: 37 | E7: =D7*C7*'Dados do Contrato '!$F$12 -> 203.5
A8: Escavadeira 345 GC | B8: 1 | C8: 1 | D8: 39 | E8: =D8*C8*'Dados do Contrato '!$F$12 -> 214.5
A9: Trator de esteiras (N) | B9: 1 | C9: 1 | D9: 28 | E9: =D9*C9*'Dados do Contrato '!$F$12 -> 154 | F9: =D9*$F$4 -> 0 | G9: =D9+F9 -> 28 | H9: =G9*'Dados do Contrato '!F12 -> 154
A10: Trator de esteiras (T) | B10: 1 | C10: 1 | D10: 39 | E10: =D10*C10*'Dados do Contrato '!$F$12 -> 214.5 | F10: =D10*$F$4 -> 0 | G10: =D10+F10 -> 39
A11: Patrol | B11: 1 | C11: 1 | D11: 17 | E11: =D11*C11*'Dados do Contrato '!$F$12 -> 93.5
A12: Grade | B12: 1 | C12: 1 | D12: 15 | E12: =D12*C12*'Dados do Contrato '!$F$12 -> 82.5
A13: Rolo Compactador | B13: 1 | C13: 1 | D13: 15 | E13: =D13*C13*'Dados do Contrato '!$F$12 -> 82.5
A14: Caminhão Pipa | B14: 1 | C14: 1 | D14: 8 | E14: =D14*C14*'Dados do Contrato '!$F$12 -> 44
